neural_feature_importance/__init__.py
neural_feature_importance/callbacks.py
neural_feature_importance/conv_callbacks.py
neural_feature_importance/embedding_callbacks.py
neural_feature_importance/utils/__init__.py
neural_feature_importance/utils/monitors.py
neural_feature_importance-0.9.1.dist-info/licenses/LICENSE
neural_feature_importance-0.9.1.dist-info/METADATA
neural_feature_importance-0.9.1.dist-info/WHEEL
neural_feature_importance-0.9.1.dist-info/top_level.txt
neural_feature_importance-0.9.1.dist-info/RECORD
