Metadata-Version: 2.4
Name: neural-feature-importance
Version: 0.9.1
Summary: Variance-based feature importance for Neural Networks using callbacks for Keras and PyTorch
Author: CR de Sá
Requires-Python: >=3.10
License-File: LICENSE
Requires-Dist: numpy
Provides-Extra: tensorflow
Requires-Dist: tensorflow; extra == "tensorflow"
Provides-Extra: torch
Requires-Dist: torch; extra == "torch"
Dynamic: license-file
